{
  "db_name": "SQLite",
  "query": "UPDATE organization SET \n                 nimi = ?, katuosoite = ?, postinumero = ?, postitoimipaikka = ?,\n                 puhelinnumero = ?, sahkoposti = ?, y_tunnus = ?, pankkitili = ?, bic = ?,\n                 updated_at = CURRENT_TIMESTAMP\n                 WHERE id = (SELECT id FROM organization LIMIT 1)",
  "describe": {
    "columns": [],
    "parameters": {
      "Right": 9
    },
    "nullable": []
  },
  "hash": "db8f19d75d335c63a57c68505ce91ecca7b2fc07bac8fa4900d548e9c9d13a68"
}
